bootstrap_italia_template/__init__.py
bootstrap_italia_template/apps.py
bootstrap_italia_template/settings.py
bootstrap_italia_template/widgets.py
bootstrap_italia_template/static/_virtual/_commonjsHelpers.js
bootstrap_italia_template/static/_virtual/_commonjsHelpers.js.map
bootstrap_italia_template/static/assets/upload-drag-drop-icon.svg
bootstrap_italia_template/static/css/bootstrap-italia.min.css
bootstrap_italia_template/static/css/bootstrap-italia.min.css.map
bootstrap_italia_template/static/fonts/Lora/OFL.txt
bootstrap_italia_template/static/fonts/Lora/lora-v20-latin-ext_latin-700.eot
bootstrap_italia_template/static/fonts/Lora/lora-v20-latin-ext_latin-700.svg
bootstrap_italia_template/static/fonts/Lora/lora-v20-latin-ext_latin-700.ttf
bootstrap_italia_template/static/fonts/Lora/lora-v20-latin-ext_latin-700.woff
bootstrap_italia_template/static/fonts/Lora/lora-v20-latin-ext_latin-700.woff2
bootstrap_italia_template/static/fonts/Lora/lora-v20-latin-ext_latin-700italic.eot
bootstrap_italia_template/static/fonts/Lora/lora-v20-latin-ext_latin-700italic.svg
bootstrap_italia_template/static/fonts/Lora/lora-v20-latin-ext_latin-700italic.ttf
bootstrap_italia_template/static/fonts/Lora/lora-v20-latin-ext_latin-700italic.woff
bootstrap_italia_template/static/fonts/Lora/lora-v20-latin-ext_latin-700italic.woff2
bootstrap_italia_template/static/fonts/Lora/lora-v20-latin-ext_latin-italic.eot
bootstrap_italia_template/static/fonts/Lora/lora-v20-latin-ext_latin-italic.svg
bootstrap_italia_template/static/fonts/Lora/lora-v20-latin-ext_latin-italic.ttf
bootstrap_italia_template/static/fonts/Lora/lora-v20-latin-ext_latin-italic.woff
bootstrap_italia_template/static/fonts/Lora/lora-v20-latin-ext_latin-italic.woff2
bootstrap_italia_template/static/fonts/Lora/lora-v20-latin-ext_latin-regular.eot
bootstrap_italia_template/static/fonts/Lora/lora-v20-latin-ext_latin-regular.svg
bootstrap_italia_template/static/fonts/Lora/lora-v20-latin-ext_latin-regular.ttf
design_django_theme-2.15.2.dist-info/licenses/AUTHORS
design_django_theme-2.15.2.dist-info/licenses/LICENSE
design_django_theme-2.15.2.dist-info/METADATA
design_django_theme-2.15.2.dist-info/WHEEL
design_django_theme-2.15.2.dist-info/top_level.txt
design_django_theme-2.15.2.dist-info/RECORD
