Metadata-Version: 2.4
Name: design-django-theme
Version: 2.15.2
Summary: Bootstrap Italia template for Django
Home-page: https://github.com/italia/design-django-theme
Author: Giuseppe De Marco, Francesco Filicetti
Author-email: giuseppe.demarco@unical.it, francesco.filicetti@unical.it
License: 3-clause BSD
Classifier: Environment :: Web Environment
Classifier: Framework :: Django
Classifier: Framework :: Django :: 2.0
Classifier: Framework :: Django :: 3.0
Classifier: Framework :: Django :: 4.0
Classifier: Framework :: Django :: 5.0
Classifier: Intended Audience :: Developers
Classifier: License :: OSI Approved :: Apache Software License
Classifier: Operating System :: OS Independent
Classifier: Programming Language :: Python
Classifier: Programming Language :: Python :: 3
License-File: LICENSE
License-File: AUTHORS
Requires-Dist: django
Dynamic: author
Dynamic: author-email
Dynamic: classifier
Dynamic: description
Dynamic: description-content-type
Dynamic: home-page
Dynamic: license
Dynamic: license-file
Dynamic: requires-dist
Dynamic: summary
